package org.apache.jsp.static_.common;

import java.util.HashSet;
import java.util.Map;
import java.util.Set;
import javax.el.ExpressionFactory;
import javax.servlet.ServletConfig;
import javax.servlet.jsp.JspApplicationContext;
import javax.servlet.jsp.JspFactory;
import org.apache.jasper.runtime.HttpJspBase;
import org.apache.jasper.runtime.InstanceManagerFactory;
import org.apache.jasper.runtime.JspSourceDependent;
import org.apache.jasper.runtime.JspSourceImports;
import org.apache.tomcat.InstanceManager;

public final class skin_002dconfig_jsp extends HttpJspBase implements JspSourceDependent, JspSourceImports {
	/* 20 */ private static final JspFactory _jspxFactory = JspFactory.getDefaultFactory();

	private static Map<String, Long> _jspx_dependants;

	/* 29 */ private static final Set<String> _jspx_imports_packages = new HashSet();

	/* 30 */ static {
		_jspx_imports_packages.add("javax.servlet");
		/* 31 */ _jspx_imports_packages.add("javax.servlet.http");
		/* 32 */ _jspx_imports_packages.add("javax.servlet.jsp");
	}

	/* 33 */ private static final Set<String> _jspx_imports_classes = null;

	private volatile ExpressionFactory _el_expressionfactory;
	private volatile InstanceManager _jsp_instancemanager;

	public Map<String, Long> getDependants() {
		/* 40 */ return _jspx_dependants;
	}

	public Set<String> getPackageImports() {
		/* 44 */ return _jspx_imports_packages;
	}

	public Set<String> getClassImports() {
		/* 48 */ return _jspx_imports_classes;
	}

	public ExpressionFactory _jsp_getExpressionFactory() {
		/* 52 */ if (this._el_expressionfactory == null) {
			/* 53 */ synchronized (this) {
				/* 54 */ if (this._el_expressionfactory == null) {
					/* 55 */ this._el_expressionfactory = _jspxFactory
							.getJspApplicationContext(getServletConfig().getServletContext()).getExpressionFactory();
				}
			}
		}
		/* 59 */ return this._el_expressionfactory;
	}

	public InstanceManager _jsp_getInstanceManager() {
		/* 63 */ if (this._jsp_instancemanager == null) {
			/* 64 */ synchronized (this) {
				/* 65 */ if (this._jsp_instancemanager == null) {
					/* 66 */ this._jsp_instancemanager = InstanceManagerFactory.getInstanceManager(getServletConfig());
				}
			}
		}
		/* 70 */ return this._jsp_instancemanager;
	}

	public void _jspInit() {
	}

	public void _jspDestroy() {
	}

	/* Error */
	public void _jspService(javax.servlet.http.HttpServletRequest request,
			javax.servlet.http.HttpServletResponse response)
					throws java.io.IOException, javax.servlet.ServletException {
		// Byte code:
		// 0: aload_1
		// 1: invokeinterface 114 1 0
		// 6: astore_3
		// 7: ldc 120
		// 9: aload_3
		// 10: invokevirtual 122 java/lang/String:equals (Ljava/lang/Object;)Z
		// 13: ifne +48 -> 61
		// 16: ldc 127
		// 18: aload_3
		// 19: invokevirtual 122 java/lang/String:equals (Ljava/lang/Object;)Z
		// 22: ifne +39 -> 61
		// 25: ldc -127
		// 27: aload_3
		// 28: invokevirtual 122 java/lang/String:equals (Ljava/lang/Object;)Z
		// 31: ifne +30 -> 61
		// 34: getstatic 131 javax/servlet/DispatcherType:ERROR
		// Ljavax/servlet/DispatcherType;
		// 37: aload_1
		// 38: invokeinterface 137 1 0
		// 43: invokevirtual 141 javax/servlet/DispatcherType:equals
		// (Ljava/lang/Object;)Z
		// 46: ifne +15 -> 61
		// 49: aload_2
		// 50: sipush 405
		// 53: ldc -114
		// 55: invokeinterface 144 3 0
		// 60: return
		// 61: aconst_null
		// 62: astore 5
		// 64: aconst_null
		// 65: astore 6
		// 67: aconst_null
		// 68: astore 7
		// 70: aload_2
		// 71: ldc -106
		// 73: invokeinterface 152 2 0
		// 78: getstatic 32
		// org/apache/jsp/static_/common/skin_002dconfig_jsp:_jspxFactory
		// Ljavax/servlet/jsp/JspFactory;
		// 81: aload_0
		// 82: aload_1
		// 83: aload_2
		// 84: aconst_null
		// 85: iconst_1
		// 86: sipush 8192
		// 89: iconst_1
		// 90: invokevirtual 156 javax/servlet/jsp/JspFactory:getPageContext
		// (Ljavax/servlet/Servlet;Ljavax/servlet/ServletRequest;Ljavax/servlet/ServletResponse;Ljava/lang/String;ZIZ)Ljavax/servlet/jsp/PageContext;
		// 93: astore 4
		// 95: aload 4
		// 97: astore 7
		// 99: aload 4
		// 101: invokevirtual 160
		// javax/servlet/jsp/PageContext:getServletContext
		// ()Ljavax/servlet/ServletContext;
		// 104: pop
		// 105: aload 4
		// 107: invokevirtual 163 javax/servlet/jsp/PageContext:getServletConfig
		// ()Ljavax/servlet/ServletConfig;
		// 110: pop
		// 111: aload 4
		// 113: invokevirtual 164 javax/servlet/jsp/PageContext:getSession
		// ()Ljavax/servlet/http/HttpSession;
		// 116: pop
		// 117: aload 4
		// 119: invokevirtual 168 javax/servlet/jsp/PageContext:getOut
		// ()Ljavax/servlet/jsp/JspWriter;
		// 122: astore 5
		// 124: aload 5
		// 126: astore 6
		// 128: aload 5
		// 130: ldc -84
		// 132: invokevirtual 174 javax/servlet/jsp/JspWriter:write
		// (Ljava/lang/String;)V
		// 135: aload 5
		// 137: ldc -77
		// 139: invokevirtual 174 javax/servlet/jsp/JspWriter:write
		// (Ljava/lang/String;)V
		// 142: aload 5
		// 144: ldc -75
		// 146: invokevirtual 174 javax/servlet/jsp/JspWriter:write
		// (Ljava/lang/String;)V
		// 149: aload 5
		// 151: ldc -73
		// 153: invokevirtual 174 javax/servlet/jsp/JspWriter:write
		// (Ljava/lang/String;)V
		// 156: aload 5
		// 158: ldc -71
		// 160: invokevirtual 174 javax/servlet/jsp/JspWriter:write
		// (Ljava/lang/String;)V
		// 163: aload 5
		// 165: ldc -69
		// 167: invokevirtual 174 javax/servlet/jsp/JspWriter:write
		// (Ljava/lang/String;)V
		// 170: aload 5
		// 172: ldc -67
		// 174: invokevirtual 174 javax/servlet/jsp/JspWriter:write
		// (Ljava/lang/String;)V
		// 177: aload 5
		// 179: ldc -65
		// 181: invokevirtual 174 javax/servlet/jsp/JspWriter:write
		// (Ljava/lang/String;)V
		// 184: aload 5
		// 186: ldc -63
		// 188: invokevirtual 174 javax/servlet/jsp/JspWriter:write
		// (Ljava/lang/String;)V
		// 191: aload 5
		// 193: ldc -61
		// 195: invokevirtual 174 javax/servlet/jsp/JspWriter:write
		// (Ljava/lang/String;)V
		// 198: aload 5
		// 200: ldc -59
		// 202: invokevirtual 174 javax/servlet/jsp/JspWriter:write
		// (Ljava/lang/String;)V
		// 205: aload 5
		// 207: ldc -57
		// 209: invokevirtual 174 javax/servlet/jsp/JspWriter:write
		// (Ljava/lang/String;)V
		// 212: aload 5
		// 214: ldc -84
		// 216: invokevirtual 174 javax/servlet/jsp/JspWriter:write
		// (Ljava/lang/String;)V
		// 219: aload 5
		// 221: ldc -55
		// 223: invokevirtual 174 javax/servlet/jsp/JspWriter:write
		// (Ljava/lang/String;)V
		// 226: aload 5
		// 228: ldc -53
		// 230: invokevirtual 174 javax/servlet/jsp/JspWriter:write
		// (Ljava/lang/String;)V
		// 233: aload 5
		// 235: ldc -51
		// 237: invokevirtual 174 javax/servlet/jsp/JspWriter:write
		// (Ljava/lang/String;)V
		// 240: aload 5
		// 242: ldc -49
		// 244: invokevirtual 174 javax/servlet/jsp/JspWriter:write
		// (Ljava/lang/String;)V
		// 247: aload 5
		// 249: ldc -47
		// 251: invokevirtual 174 javax/servlet/jsp/JspWriter:write
		// (Ljava/lang/String;)V
		// 254: aload 5
		// 256: ldc -45
		// 258: invokevirtual 174 javax/servlet/jsp/JspWriter:write
		// (Ljava/lang/String;)V
		// 261: aload 5
		// 263: ldc -43
		// 265: invokevirtual 174 javax/servlet/jsp/JspWriter:write
		// (Ljava/lang/String;)V
		// 268: aload 5
		// 270: ldc -41
		// 272: invokevirtual 174 javax/servlet/jsp/JspWriter:write
		// (Ljava/lang/String;)V
		// 275: aload 5
		// 277: ldc -39
		// 279: invokevirtual 174 javax/servlet/jsp/JspWriter:write
		// (Ljava/lang/String;)V
		// 282: aload 5
		// 284: ldc -37
		// 286: invokevirtual 174 javax/servlet/jsp/JspWriter:write
		// (Ljava/lang/String;)V
		// 289: aload 5
		// 291: ldc -63
		// 293: invokevirtual 174 javax/servlet/jsp/JspWriter:write
		// (Ljava/lang/String;)V
		// 296: aload 5
		// 298: ldc -61
		// 300: invokevirtual 174 javax/servlet/jsp/JspWriter:write
		// (Ljava/lang/String;)V
		// 303: aload 5
		// 305: ldc -35
		// 307: invokevirtual 174 javax/servlet/jsp/JspWriter:write
		// (Ljava/lang/String;)V
		// 310: aload 5
		// 312: ldc -57
		// 314: invokevirtual 174 javax/servlet/jsp/JspWriter:write
		// (Ljava/lang/String;)V
		// 317: aload 5
		// 319: ldc -84
		// 321: invokevirtual 174 javax/servlet/jsp/JspWriter:write
		// (Ljava/lang/String;)V
		// 324: aload 5
		// 326: ldc -55
		// 328: invokevirtual 174 javax/servlet/jsp/JspWriter:write
		// (Ljava/lang/String;)V
		// 331: aload 5
		// 333: ldc -53
		// 335: invokevirtual 174 javax/servlet/jsp/JspWriter:write
		// (Ljava/lang/String;)V
		// 338: aload 5
		// 340: ldc -33
		// 342: invokevirtual 174 javax/servlet/jsp/JspWriter:write
		// (Ljava/lang/String;)V
		// 345: aload 5
		// 347: ldc -31
		// 349: invokevirtual 174 javax/servlet/jsp/JspWriter:write
		// (Ljava/lang/String;)V
		// 352: aload 5
		// 354: ldc -47
		// 356: invokevirtual 174 javax/servlet/jsp/JspWriter:write
		// (Ljava/lang/String;)V
		// 359: aload 5
		// 361: ldc -45
		// 363: invokevirtual 174 javax/servlet/jsp/JspWriter:write
		// (Ljava/lang/String;)V
		// 366: aload 5
		// 368: ldc -43
		// 370: invokevirtual 174 javax/servlet/jsp/JspWriter:write
		// (Ljava/lang/String;)V
		// 373: aload 5
		// 375: ldc -41
		// 377: invokevirtual 174 javax/servlet/jsp/JspWriter:write
		// (Ljava/lang/String;)V
		// 380: aload 5
		// 382: ldc -39
		// 384: invokevirtual 174 javax/servlet/jsp/JspWriter:write
		// (Ljava/lang/String;)V
		// 387: aload 5
		// 389: ldc -37
		// 391: invokevirtual 174 javax/servlet/jsp/JspWriter:write
		// (Ljava/lang/String;)V
		// 394: aload 5
		// 396: ldc -63
		// 398: invokevirtual 174 javax/servlet/jsp/JspWriter:write
		// (Ljava/lang/String;)V
		// 401: aload 5
		// 403: ldc -61
		// 405: invokevirtual 174 javax/servlet/jsp/JspWriter:write
		// (Ljava/lang/String;)V
		// 408: aload 5
		// 410: ldc -29
		// 412: invokevirtual 174 javax/servlet/jsp/JspWriter:write
		// (Ljava/lang/String;)V
		// 415: aload 5
		// 417: ldc -57
		// 419: invokevirtual 174 javax/servlet/jsp/JspWriter:write
		// (Ljava/lang/String;)V
		// 422: aload 5
		// 424: ldc -84
		// 426: invokevirtual 174 javax/servlet/jsp/JspWriter:write
		// (Ljava/lang/String;)V
		// 429: aload 5
		// 431: ldc -55
		// 433: invokevirtual 174 javax/servlet/jsp/JspWriter:write
		// (Ljava/lang/String;)V
		// 436: aload 5
		// 438: ldc -53
		// 440: invokevirtual 174 javax/servlet/jsp/JspWriter:write
		// (Ljava/lang/String;)V
		// 443: aload 5
		// 445: ldc -27
		// 447: invokevirtual 174 javax/servlet/jsp/JspWriter:write
		// (Ljava/lang/String;)V
		// 450: aload 5
		// 452: ldc -25
		// 454: invokevirtual 174 javax/servlet/jsp/JspWriter:write
		// (Ljava/lang/String;)V
		// 457: aload 5
		// 459: ldc -47
		// 461: invokevirtual 174 javax/servlet/jsp/JspWriter:write
		// (Ljava/lang/String;)V
		// 464: aload 5
		// 466: ldc -45
		// 468: invokevirtual 174 javax/servlet/jsp/JspWriter:write
		// (Ljava/lang/String;)V
		// 471: aload 5
		// 473: ldc -43
		// 475: invokevirtual 174 javax/servlet/jsp/JspWriter:write
		// (Ljava/lang/String;)V
		// 478: aload 5
		// 480: ldc -41
		// 482: invokevirtual 174 javax/servlet/jsp/JspWriter:write
		// (Ljava/lang/String;)V
		// 485: aload 5
		// 487: ldc -39
		// 489: invokevirtual 174 javax/servlet/jsp/JspWriter:write
		// (Ljava/lang/String;)V
		// 492: aload 5
		// 494: ldc -37
		// 496: invokevirtual 174 javax/servlet/jsp/JspWriter:write
		// (Ljava/lang/String;)V
		// 499: aload 5
		// 501: ldc -23
		// 503: invokevirtual 174 javax/servlet/jsp/JspWriter:write
		// (Ljava/lang/String;)V
		// 506: aload 5
		// 508: ldc -21
		// 510: invokevirtual 174 javax/servlet/jsp/JspWriter:write
		// (Ljava/lang/String;)V
		// 513: aload 5
		// 515: ldc -19
		// 517: invokevirtual 174 javax/servlet/jsp/JspWriter:write
		// (Ljava/lang/String;)V
		// 520: aload 5
		// 522: ldc -17
		// 524: invokevirtual 174 javax/servlet/jsp/JspWriter:write
		// (Ljava/lang/String;)V
		// 527: aload 5
		// 529: ldc -15
		// 531: invokevirtual 174 javax/servlet/jsp/JspWriter:write
		// (Ljava/lang/String;)V
		// 534: aload 5
		// 536: ldc -13
		// 538: invokevirtual 174 javax/servlet/jsp/JspWriter:write
		// (Ljava/lang/String;)V
		// 541: aload 5
		// 543: ldc -57
		// 545: invokevirtual 174 javax/servlet/jsp/JspWriter:write
		// (Ljava/lang/String;)V
		// 548: aload 5
		// 550: ldc -37
		// 552: invokevirtual 174 javax/servlet/jsp/JspWriter:write
		// (Ljava/lang/String;)V
		// 555: aload 5
		// 557: ldc -11
		// 559: invokevirtual 174 javax/servlet/jsp/JspWriter:write
		// (Ljava/lang/String;)V
		// 562: aload 5
		// 564: ldc -19
		// 566: invokevirtual 174 javax/servlet/jsp/JspWriter:write
		// (Ljava/lang/String;)V
		// 569: aload 5
		// 571: ldc -9
		// 573: invokevirtual 174 javax/servlet/jsp/JspWriter:write
		// (Ljava/lang/String;)V
		// 576: aload 5
		// 578: ldc -7
		// 580: invokevirtual 174 javax/servlet/jsp/JspWriter:write
		// (Ljava/lang/String;)V
		// 583: aload 5
		// 585: ldc -5
		// 587: invokevirtual 174 javax/servlet/jsp/JspWriter:write
		// (Ljava/lang/String;)V
		// 590: aload 5
		// 592: ldc -57
		// 594: invokevirtual 174 javax/servlet/jsp/JspWriter:write
		// (Ljava/lang/String;)V
		// 597: aload 5
		// 599: ldc -37
		// 601: invokevirtual 174 javax/servlet/jsp/JspWriter:write
		// (Ljava/lang/String;)V
		// 604: aload 5
		// 606: ldc -3
		// 608: invokevirtual 174 javax/servlet/jsp/JspWriter:write
		// (Ljava/lang/String;)V
		// 611: aload 5
		// 613: ldc -19
		// 615: invokevirtual 174 javax/servlet/jsp/JspWriter:write
		// (Ljava/lang/String;)V
		// 618: aload 5
		// 620: ldc -1
		// 622: invokevirtual 174 javax/servlet/jsp/JspWriter:write
		// (Ljava/lang/String;)V
		// 625: aload 5
		// 627: ldc_w 257
		// 630: invokevirtual 174 javax/servlet/jsp/JspWriter:write
		// (Ljava/lang/String;)V
		// 633: aload 5
		// 635: ldc -5
		// 637: invokevirtual 174 javax/servlet/jsp/JspWriter:write
		// (Ljava/lang/String;)V
		// 640: aload 5
		// 642: ldc -57
		// 644: invokevirtual 174 javax/servlet/jsp/JspWriter:write
		// (Ljava/lang/String;)V
		// 647: aload 5
		// 649: ldc -37
		// 651: invokevirtual 174 javax/servlet/jsp/JspWriter:write
		// (Ljava/lang/String;)V
		// 654: aload 5
		// 656: ldc -69
		// 658: invokevirtual 174 javax/servlet/jsp/JspWriter:write
		// (Ljava/lang/String;)V
		// 661: aload 5
		// 663: ldc_w 259
		// 666: invokevirtual 174 javax/servlet/jsp/JspWriter:write
		// (Ljava/lang/String;)V
		// 669: aload 5
		// 671: ldc_w 261
		// 674: invokevirtual 174 javax/servlet/jsp/JspWriter:write
		// (Ljava/lang/String;)V
		// 677: aload 5
		// 679: ldc_w 263
		// 682: invokevirtual 174 javax/servlet/jsp/JspWriter:write
		// (Ljava/lang/String;)V
		// 685: aload 5
		// 687: ldc_w 265
		// 690: invokevirtual 174 javax/servlet/jsp/JspWriter:write
		// (Ljava/lang/String;)V
		// 693: aload 5
		// 695: ldc_w 267
		// 698: invokevirtual 174 javax/servlet/jsp/JspWriter:write
		// (Ljava/lang/String;)V
		// 701: aload 5
		// 703: ldc_w 269
		// 706: invokevirtual 174 javax/servlet/jsp/JspWriter:write
		// (Ljava/lang/String;)V
		// 709: aload 5
		// 711: ldc_w 271
		// 714: invokevirtual 174 javax/servlet/jsp/JspWriter:write
		// (Ljava/lang/String;)V
		// 717: aload 5
		// 719: ldc_w 273
		// 722: invokevirtual 174 javax/servlet/jsp/JspWriter:write
		// (Ljava/lang/String;)V
		// 725: aload 5
		// 727: ldc_w 275
		// 730: invokevirtual 174 javax/servlet/jsp/JspWriter:write
		// (Ljava/lang/String;)V
		// 733: aload 5
		// 735: ldc_w 277
		// 738: invokevirtual 174 javax/servlet/jsp/JspWriter:write
		// (Ljava/lang/String;)V
		// 741: aload 5
		// 743: ldc -84
		// 745: invokevirtual 174 javax/servlet/jsp/JspWriter:write
		// (Ljava/lang/String;)V
		// 748: aload 5
		// 750: ldc_w 279
		// 753: invokevirtual 174 javax/servlet/jsp/JspWriter:write
		// (Ljava/lang/String;)V
		// 756: aload 5
		// 758: ldc_w 281
		// 761: invokevirtual 174 javax/servlet/jsp/JspWriter:write
		// (Ljava/lang/String;)V
		// 764: aload 5
		// 766: ldc_w 283
		// 769: invokevirtual 174 javax/servlet/jsp/JspWriter:write
		// (Ljava/lang/String;)V
		// 772: aload 5
		// 774: ldc -84
		// 776: invokevirtual 174 javax/servlet/jsp/JspWriter:write
		// (Ljava/lang/String;)V
		// 779: aload 5
		// 781: ldc_w 279
		// 784: invokevirtual 174 javax/servlet/jsp/JspWriter:write
		// (Ljava/lang/String;)V
		// 787: aload 5
		// 789: ldc_w 285
		// 792: invokevirtual 174 javax/servlet/jsp/JspWriter:write
		// (Ljava/lang/String;)V
		// 795: aload 5
		// 797: ldc_w 283
		// 800: invokevirtual 174 javax/servlet/jsp/JspWriter:write
		// (Ljava/lang/String;)V
		// 803: aload 5
		// 805: ldc_w 287
		// 808: invokevirtual 174 javax/servlet/jsp/JspWriter:write
		// (Ljava/lang/String;)V
		// 811: aload 5
		// 813: ldc_w 289
		// 816: invokevirtual 174 javax/servlet/jsp/JspWriter:write
		// (Ljava/lang/String;)V
		// 819: aload 5
		// 821: ldc_w 291
		// 824: invokevirtual 174 javax/servlet/jsp/JspWriter:write
		// (Ljava/lang/String;)V
		// 827: aload 5
		// 829: ldc -84
		// 831: invokevirtual 174 javax/servlet/jsp/JspWriter:write
		// (Ljava/lang/String;)V
		// 834: aload 5
		// 836: ldc_w 279
		// 839: invokevirtual 174 javax/servlet/jsp/JspWriter:write
		// (Ljava/lang/String;)V
		// 842: aload 5
		// 844: ldc_w 293
		// 847: invokevirtual 174 javax/servlet/jsp/JspWriter:write
		// (Ljava/lang/String;)V
		// 850: aload 5
		// 852: ldc_w 283
		// 855: invokevirtual 174 javax/servlet/jsp/JspWriter:write
		// (Ljava/lang/String;)V
		// 858: aload 5
		// 860: ldc_w 295
		// 863: invokevirtual 174 javax/servlet/jsp/JspWriter:write
		// (Ljava/lang/String;)V
		// 866: aload 5
		// 868: ldc_w 297
		// 871: invokevirtual 174 javax/servlet/jsp/JspWriter:write
		// (Ljava/lang/String;)V
		// 874: aload 5
		// 876: ldc -84
		// 878: invokevirtual 174 javax/servlet/jsp/JspWriter:write
		// (Ljava/lang/String;)V
		// 881: aload 5
		// 883: ldc -84
		// 885: invokevirtual 174 javax/servlet/jsp/JspWriter:write
		// (Ljava/lang/String;)V
		// 888: aload 5
		// 890: ldc_w 299
		// 893: invokevirtual 174 javax/servlet/jsp/JspWriter:write
		// (Ljava/lang/String;)V
		// 896: aload 5
		// 898: ldc_w 301
		// 901: invokevirtual 174 javax/servlet/jsp/JspWriter:write
		// (Ljava/lang/String;)V
		// 904: aload 5
		// 906: ldc_w 303
		// 909: invokevirtual 174 javax/servlet/jsp/JspWriter:write
		// (Ljava/lang/String;)V
		// 912: aload 5
		// 914: ldc_w 305
		// 917: invokevirtual 174 javax/servlet/jsp/JspWriter:write
		// (Ljava/lang/String;)V
		// 920: aload 5
		// 922: ldc_w 307
		// 925: invokevirtual 174 javax/servlet/jsp/JspWriter:write
		// (Ljava/lang/String;)V
		// 928: aload 5
		// 930: ldc -84
		// 932: invokevirtual 174 javax/servlet/jsp/JspWriter:write
		// (Ljava/lang/String;)V
		// 935: aload 5
		// 937: ldc_w 279
		// 940: invokevirtual 174 javax/servlet/jsp/JspWriter:write
		// (Ljava/lang/String;)V
		// 943: aload 5
		// 945: ldc_w 309
		// 948: invokevirtual 174 javax/servlet/jsp/JspWriter:write
		// (Ljava/lang/String;)V
		// 951: aload 5
		// 953: ldc_w 283
		// 956: invokevirtual 174 javax/servlet/jsp/JspWriter:write
		// (Ljava/lang/String;)V
		// 959: aload 5
		// 961: ldc -84
		// 963: invokevirtual 174 javax/servlet/jsp/JspWriter:write
		// (Ljava/lang/String;)V
		// 966: aload 5
		// 968: ldc_w 287
		// 971: invokevirtual 174 javax/servlet/jsp/JspWriter:write
		// (Ljava/lang/String;)V
		// 974: aload 5
		// 976: ldc_w 311
		// 979: invokevirtual 174 javax/servlet/jsp/JspWriter:write
		// (Ljava/lang/String;)V
		// 982: aload 5
		// 984: ldc_w 307
		// 987: invokevirtual 174 javax/servlet/jsp/JspWriter:write
		// (Ljava/lang/String;)V
		// 990: aload 5
		// 992: ldc -84
		// 994: invokevirtual 174 javax/servlet/jsp/JspWriter:write
		// (Ljava/lang/String;)V
		// 997: aload 5
		// 999: ldc_w 279
		// 1002: invokevirtual 174 javax/servlet/jsp/JspWriter:write
		// (Ljava/lang/String;)V
		// 1005: aload 5
		// 1007: ldc_w 313
		// 1010: invokevirtual 174 javax/servlet/jsp/JspWriter:write
		// (Ljava/lang/String;)V
		// 1013: aload 5
		// 1015: ldc_w 283
		// 1018: invokevirtual 174 javax/servlet/jsp/JspWriter:write
		// (Ljava/lang/String;)V
		// 1021: aload 5
		// 1023: ldc_w 295
		// 1026: invokevirtual 174 javax/servlet/jsp/JspWriter:write
		// (Ljava/lang/String;)V
		// 1029: aload 5
		// 1031: ldc_w 297
		// 1034: invokevirtual 174 javax/servlet/jsp/JspWriter:write
		// (Ljava/lang/String;)V
		// 1037: aload 5
		// 1039: ldc -84
		// 1041: invokevirtual 174 javax/servlet/jsp/JspWriter:write
		// (Ljava/lang/String;)V
		// 1044: aload 5
		// 1046: ldc_w 315
		// 1049: invokevirtual 174 javax/servlet/jsp/JspWriter:write
		// (Ljava/lang/String;)V
		// 1052: aload 5
		// 1054: ldc_w 317
		// 1057: invokevirtual 174 javax/servlet/jsp/JspWriter:write
		// (Ljava/lang/String;)V
		// 1060: aload 5
		// 1062: ldc_w 319
		// 1065: invokevirtual 174 javax/servlet/jsp/JspWriter:write
		// (Ljava/lang/String;)V
		// 1068: aload 5
		// 1070: ldc_w 321
		// 1073: invokevirtual 174 javax/servlet/jsp/JspWriter:write
		// (Ljava/lang/String;)V
		// 1076: aload 5
		// 1078: ldc_w 323
		// 1081: invokevirtual 174 javax/servlet/jsp/JspWriter:write
		// (Ljava/lang/String;)V
		// 1084: aload 5
		// 1086: ldc_w 289
		// 1089: invokevirtual 174 javax/servlet/jsp/JspWriter:write
		// (Ljava/lang/String;)V
		// 1092: aload 5
		// 1094: ldc_w 291
		// 1097: invokevirtual 174 javax/servlet/jsp/JspWriter:write
		// (Ljava/lang/String;)V
		// 1100: aload 5
		// 1102: ldc_w 279
		// 1105: invokevirtual 174 javax/servlet/jsp/JspWriter:write
		// (Ljava/lang/String;)V
		// 1108: aload 5
		// 1110: ldc_w 293
		// 1113: invokevirtual 174 javax/servlet/jsp/JspWriter:write
		// (Ljava/lang/String;)V
		// 1116: aload 5
		// 1118: ldc_w 283
		// 1121: invokevirtual 174 javax/servlet/jsp/JspWriter:write
		// (Ljava/lang/String;)V
		// 1124: aload 5
		// 1126: ldc -84
		// 1128: invokevirtual 174 javax/servlet/jsp/JspWriter:write
		// (Ljava/lang/String;)V
		// 1131: aload 5
		// 1133: ldc -84
		// 1135: invokevirtual 174 javax/servlet/jsp/JspWriter:write
		// (Ljava/lang/String;)V
		// 1138: aload 5
		// 1140: ldc_w 279
		// 1143: invokevirtual 174 javax/servlet/jsp/JspWriter:write
		// (Ljava/lang/String;)V
		// 1146: aload 5
		// 1148: ldc_w 325
		// 1151: invokevirtual 174 javax/servlet/jsp/JspWriter:write
		// (Ljava/lang/String;)V
		// 1154: aload 5
		// 1156: ldc_w 283
		// 1159: invokevirtual 174 javax/servlet/jsp/JspWriter:write
		// (Ljava/lang/String;)V
		// 1162: aload 5
		// 1164: ldc_w 287
		// 1167: invokevirtual 174 javax/servlet/jsp/JspWriter:write
		// (Ljava/lang/String;)V
		// 1170: aload 5
		// 1172: ldc_w 273
		// 1175: invokevirtual 174 javax/servlet/jsp/JspWriter:write
		// (Ljava/lang/String;)V
		// 1178: aload 5
		// 1180: ldc -84
		// 1182: invokevirtual 174 javax/servlet/jsp/JspWriter:write
		// (Ljava/lang/String;)V
		// 1185: aload 5
		// 1187: ldc_w 279
		// 1190: invokevirtual 174 javax/servlet/jsp/JspWriter:write
		// (Ljava/lang/String;)V
		// 1193: aload 5
		// 1195: ldc_w 281
		// 1198: invokevirtual 174 javax/servlet/jsp/JspWriter:write
		// (Ljava/lang/String;)V
		// 1201: aload 5
		// 1203: ldc_w 283
		// 1206: invokevirtual 174 javax/servlet/jsp/JspWriter:write
		// (Ljava/lang/String;)V
		// 1209: aload 5
		// 1211: ldc_w 295
		// 1214: invokevirtual 174 javax/servlet/jsp/JspWriter:write
		// (Ljava/lang/String;)V
		// 1217: aload 5
		// 1219: ldc_w 297
		// 1222: invokevirtual 174 javax/servlet/jsp/JspWriter:write
		// (Ljava/lang/String;)V
		// 1225: aload 5
		// 1227: ldc -84
		// 1229: invokevirtual 174 javax/servlet/jsp/JspWriter:write
		// (Ljava/lang/String;)V
		// 1232: aload 5
		// 1234: ldc_w 327
		// 1237: invokevirtual 174 javax/servlet/jsp/JspWriter:write
		// (Ljava/lang/String;)V
		// 1240: aload 5
		// 1242: ldc_w 329
		// 1245: invokevirtual 174 javax/servlet/jsp/JspWriter:write
		// (Ljava/lang/String;)V
		// 1248: aload 5
		// 1250: ldc_w 331
		// 1253: invokevirtual 174 javax/servlet/jsp/JspWriter:write
		// (Ljava/lang/String;)V
		// 1256: aload 5
		// 1258: ldc_w 333
		// 1261: invokevirtual 174 javax/servlet/jsp/JspWriter:write
		// (Ljava/lang/String;)V
		// 1264: aload 5
		// 1266: ldc_w 297
		// 1269: invokevirtual 174 javax/servlet/jsp/JspWriter:write
		// (Ljava/lang/String;)V
		// 1272: aload 5
		// 1274: ldc -84
		// 1276: invokevirtual 174 javax/servlet/jsp/JspWriter:write
		// (Ljava/lang/String;)V
		// 1279: aload 5
		// 1281: ldc_w 335
		// 1284: invokevirtual 174 javax/servlet/jsp/JspWriter:write
		// (Ljava/lang/String;)V
		// 1287: aload 5
		// 1289: ldc_w 337
		// 1292: invokevirtual 174 javax/servlet/jsp/JspWriter:write
		// (Ljava/lang/String;)V
		// 1295: aload 5
		// 1297: ldc_w 339
		// 1300: invokevirtual 174 javax/servlet/jsp/JspWriter:write
		// (Ljava/lang/String;)V
		// 1303: aload 5
		// 1305: ldc_w 341
		// 1308: invokevirtual 174 javax/servlet/jsp/JspWriter:write
		// (Ljava/lang/String;)V
		// 1311: aload 5
		// 1313: ldc_w 343
		// 1316: invokevirtual 174 javax/servlet/jsp/JspWriter:write
		// (Ljava/lang/String;)V
		// 1319: aload 5
		// 1321: ldc_w 345
		// 1324: invokevirtual 174 javax/servlet/jsp/JspWriter:write
		// (Ljava/lang/String;)V
		// 1327: aload 5
		// 1329: ldc_w 347
		// 1332: invokevirtual 174 javax/servlet/jsp/JspWriter:write
		// (Ljava/lang/String;)V
		// 1335: aload 5
		// 1337: ldc_w 349
		// 1340: ldc 123
		// 1342: aload 7
		// 1344: aconst_null
		// 1345: invokestatic 351
		// org/apache/jasper/runtime/PageContextImpl:proprietaryEvaluate
		// (Ljava/lang/String;Ljava/lang/Class;Ljavax/servlet/jsp/PageContext;Lorg/apache/jasper/runtime/ProtectedFunctionMapper;)Ljava/lang/Object;
		// 1348: checkcast 123 java/lang/String
		// 1351: invokevirtual 174 javax/servlet/jsp/JspWriter:write
		// (Ljava/lang/String;)V
		// 1354: aload 5
		// 1356: ldc_w 357
		// 1359: invokevirtual 174 javax/servlet/jsp/JspWriter:write
		// (Ljava/lang/String;)V
		// 1362: aload 5
		// 1364: ldc_w 297
		// 1367: invokevirtual 174 javax/servlet/jsp/JspWriter:write
		// (Ljava/lang/String;)V
		// 1370: aload 5
		// 1372: ldc -84
		// 1374: invokevirtual 174 javax/servlet/jsp/JspWriter:write
		// (Ljava/lang/String;)V
		// 1377: aload 5
		// 1379: ldc_w 359
		// 1382: invokevirtual 174 javax/servlet/jsp/JspWriter:write
		// (Ljava/lang/String;)V
		// 1385: aload 5
		// 1387: ldc_w 361
		// 1390: invokevirtual 174 javax/servlet/jsp/JspWriter:write
		// (Ljava/lang/String;)V
		// 1393: aload 5
		// 1395: ldc_w 341
		// 1398: invokevirtual 174 javax/servlet/jsp/JspWriter:write
		// (Ljava/lang/String;)V
		// 1401: aload 5
		// 1403: ldc_w 343
		// 1406: invokevirtual 174 javax/servlet/jsp/JspWriter:write
		// (Ljava/lang/String;)V
		// 1409: aload 5
		// 1411: ldc_w 363
		// 1414: invokevirtual 174 javax/servlet/jsp/JspWriter:write
		// (Ljava/lang/String;)V
		// 1417: aload 5
		// 1419: ldc_w 365
		// 1422: invokevirtual 174 javax/servlet/jsp/JspWriter:write
		// (Ljava/lang/String;)V
		// 1425: aload 5
		// 1427: ldc_w 349
		// 1430: ldc 123
		// 1432: aload 7
		// 1434: aconst_null
		// 1435: invokestatic 351
		// org/apache/jasper/runtime/PageContextImpl:proprietaryEvaluate
		// (Ljava/lang/String;Ljava/lang/Class;Ljavax/servlet/jsp/PageContext;Lorg/apache/jasper/runtime/ProtectedFunctionMapper;)Ljava/lang/Object;
		// 1438: checkcast 123 java/lang/String
		// 1441: invokevirtual 174 javax/servlet/jsp/JspWriter:write
		// (Ljava/lang/String;)V
		// 1444: aload 5
		// 1446: ldc_w 367
		// 1449: invokevirtual 174 javax/servlet/jsp/JspWriter:write
		// (Ljava/lang/String;)V
		// 1452: aload 5
		// 1454: ldc_w 297
		// 1457: invokevirtual 174 javax/servlet/jsp/JspWriter:write
		// (Ljava/lang/String;)V
		// 1460: aload 5
		// 1462: ldc -84
		// 1464: invokevirtual 174 javax/servlet/jsp/JspWriter:write
		// (Ljava/lang/String;)V
		// 1467: aload 5
		// 1469: ldc_w 369
		// 1472: invokevirtual 174 javax/servlet/jsp/JspWriter:write
		// (Ljava/lang/String;)V
		// 1475: aload 5
		// 1477: ldc_w 371
		// 1480: invokevirtual 174 javax/servlet/jsp/JspWriter:write
		// (Ljava/lang/String;)V
		// 1483: aload 5
		// 1485: ldc_w 345
		// 1488: invokevirtual 174 javax/servlet/jsp/JspWriter:write
		// (Ljava/lang/String;)V
		// 1491: aload 5
		// 1493: ldc_w 341
		// 1496: invokevirtual 174 javax/servlet/jsp/JspWriter:write
		// (Ljava/lang/String;)V
		// 1499: aload 5
		// 1501: ldc_w 373
		// 1504: invokevirtual 174 javax/servlet/jsp/JspWriter:write
		// (Ljava/lang/String;)V
		// 1507: aload 5
		// 1509: ldc_w 365
		// 1512: invokevirtual 174 javax/servlet/jsp/JspWriter:write
		// (Ljava/lang/String;)V
		// 1515: aload 5
		// 1517: ldc_w 349
		// 1520: ldc 123
		// 1522: aload 7
		// 1524: aconst_null
		// 1525: invokestatic 351
		// org/apache/jasper/runtime/PageContextImpl:proprietaryEvaluate
		// (Ljava/lang/String;Ljava/lang/Class;Ljavax/servlet/jsp/PageContext;Lorg/apache/jasper/runtime/ProtectedFunctionMapper;)Ljava/lang/Object;
		// 1528: checkcast 123 java/lang/String
		// 1531: invokevirtual 174 javax/servlet/jsp/JspWriter:write
		// (Ljava/lang/String;)V
		// 1534: aload 5
		// 1536: ldc_w 375
		// 1539: invokevirtual 174 javax/servlet/jsp/JspWriter:write
		// (Ljava/lang/String;)V
		// 1542: aload 5
		// 1544: ldc_w 297
		// 1547: invokevirtual 174 javax/servlet/jsp/JspWriter:write
		// (Ljava/lang/String;)V
		// 1550: aload 5
		// 1552: ldc_w 377
		// 1555: invokevirtual 174 javax/servlet/jsp/JspWriter:write
		// (Ljava/lang/String;)V
		// 1558: aload 5
		// 1560: ldc_w 379
		// 1563: invokevirtual 174 javax/servlet/jsp/JspWriter:write
		// (Ljava/lang/String;)V
		// 1566: aload 5
		// 1568: ldc_w 381
		// 1571: invokevirtual 174 javax/servlet/jsp/JspWriter:write
		// (Ljava/lang/String;)V
		// 1574: aload 5
		// 1576: ldc_w 383
		// 1579: invokevirtual 174 javax/servlet/jsp/JspWriter:write
		// (Ljava/lang/String;)V
		// 1582: aload 5
		// 1584: ldc_w 385
		// 1587: invokevirtual 174 javax/servlet/jsp/JspWriter:write
		// (Ljava/lang/String;)V
		// 1590: aload 5
		// 1592: ldc -84
		// 1594: invokevirtual 174 javax/servlet/jsp/JspWriter:write
		// (Ljava/lang/String;)V
		// 1597: aload 5
		// 1599: ldc_w 387
		// 1602: invokevirtual 174 javax/servlet/jsp/JspWriter:write
		// (Ljava/lang/String;)V
		// 1605: aload 5
		// 1607: ldc_w 389
		// 1610: invokevirtual 174 javax/servlet/jsp/JspWriter:write
		// (Ljava/lang/String;)V
		// 1613: aload 5
		// 1615: ldc_w 295
		// 1618: invokevirtual 174 javax/servlet/jsp/JspWriter:write
		// (Ljava/lang/String;)V
		// 1621: aload 5
		// 1623: ldc_w 391
		// 1626: invokevirtual 174 javax/servlet/jsp/JspWriter:write
		// (Ljava/lang/String;)V
		// 1629: aload 5
		// 1631: ldc_w 393
		// 1634: invokevirtual 174 javax/servlet/jsp/JspWriter:write
		// (Ljava/lang/String;)V
		// 1637: aload 5
		// 1639: ldc_w 295
		// 1642: invokevirtual 174 javax/servlet/jsp/JspWriter:write
		// (Ljava/lang/String;)V
		// 1645: aload 5
		// 1647: ldc_w 395
		// 1650: invokevirtual 174 javax/servlet/jsp/JspWriter:write
		// (Ljava/lang/String;)V
		// 1653: aload 5
		// 1655: ldc_w 397
		// 1658: invokevirtual 174 javax/servlet/jsp/JspWriter:write
		// (Ljava/lang/String;)V
		// 1661: aload 5
		// 1663: ldc_w 295
		// 1666: invokevirtual 174 javax/servlet/jsp/JspWriter:write
		// (Ljava/lang/String;)V
		// 1669: aload 5
		// 1671: ldc_w 399
		// 1674: invokevirtual 174 javax/servlet/jsp/JspWriter:write
		// (Ljava/lang/String;)V
		// 1677: aload 5
		// 1679: ldc_w 401
		// 1682: invokevirtual 174 javax/servlet/jsp/JspWriter:write
		// (Ljava/lang/String;)V
		// 1685: aload 5
		// 1687: ldc -84
		// 1689: invokevirtual 174 javax/servlet/jsp/JspWriter:write
		// (Ljava/lang/String;)V
		// 1692: aload 5
		// 1694: ldc_w 403
		// 1697: invokevirtual 174 javax/servlet/jsp/JspWriter:write
		// (Ljava/lang/String;)V
		// 1700: aload 5
		// 1702: ldc_w 405
		// 1705: invokevirtual 174 javax/servlet/jsp/JspWriter:write
		// (Ljava/lang/String;)V
		// 1708: aload 5
		// 1710: ldc_w 407
		// 1713: invokevirtual 174 javax/servlet/jsp/JspWriter:write
		// (Ljava/lang/String;)V
		// 1716: aload 5
		// 1718: ldc_w 399
		// 1721: invokevirtual 174 javax/servlet/jsp/JspWriter:write
		// (Ljava/lang/String;)V
		// 1724: aload 5
		// 1726: ldc_w 409
		// 1729: invokevirtual 174 javax/servlet/jsp/JspWriter:write
		// (Ljava/lang/String;)V
		// 1732: goto +105 -> 1837
		// 1735: astore 8
		// 1737: aload 8
		// 1739: instanceof 411
		// 1742: ifne +71 -> 1813
		// 1745: aload 6
		// 1747: astore 5
		// 1749: aload 5
		// 1751: ifnull +37 -> 1788
		// 1754: aload 5
		// 1756: invokevirtual 413 javax/servlet/jsp/JspWriter:getBufferSize ()I
		// 1759: ifeq +29 -> 1788
		// 1762: aload_2
		// 1763: invokeinterface 417 1 0
		// 1768: ifeq +11 -> 1779
		// 1771: aload 5
		// 1773: invokevirtual 421 javax/servlet/jsp/JspWriter:flush ()V
		// 1776: goto +12 -> 1788
		// 1779: aload 5
		// 1781: invokevirtual 424 javax/servlet/jsp/JspWriter:clearBuffer ()V
		// 1784: goto +4 -> 1788
		// 1787: pop
		// 1788: aload 7
		// 1790: ifnull +13 -> 1803
		// 1793: aload 7
		// 1795: aload 8
		// 1797: invokevirtual 427
		// javax/servlet/jsp/PageContext:handlePageException
		// (Ljava/lang/Throwable;)V
		// 1800: goto +13 -> 1813
		// 1803: new 112 javax/servlet/ServletException
		// 1806: dup
		// 1807: aload 8
		// 1809: invokespecial 431 javax/servlet/ServletException:<init>
		// (Ljava/lang/Throwable;)V
		// 1812: athrow
		// 1813: getstatic 32
		// org/apache/jsp/static_/common/skin_002dconfig_jsp:_jspxFactory
		// Ljavax/servlet/jsp/JspFactory;
		// 1816: aload 7
		// 1818: invokevirtual 433
		// javax/servlet/jsp/JspFactory:releasePageContext
		// (Ljavax/servlet/jsp/PageContext;)V
		// 1821: goto +24 -> 1845
		// 1824: astore 9
		// 1826: getstatic 32
		// org/apache/jsp/static_/common/skin_002dconfig_jsp:_jspxFactory
		// Ljavax/servlet/jsp/JspFactory;
		// 1829: aload 7
		// 1831: invokevirtual 433
		// javax/servlet/jsp/JspFactory:releasePageContext
		// (Ljavax/servlet/jsp/PageContext;)V
		// 1834: aload 9
		// 1836: athrow
		// 1837: getstatic 32
		// org/apache/jsp/static_/common/skin_002dconfig_jsp:_jspxFactory
		// Ljavax/servlet/jsp/JspFactory;
		// 1840: aload 7
		// 1842: invokevirtual 433
		// javax/servlet/jsp/JspFactory:releasePageContext
		// (Ljavax/servlet/jsp/PageContext;)V
		// 1845: return
		// Line number table:
		// Java source line #82 -> byte code offset #0
		// Java source line #83 -> byte code offset #7
		// Java source line #84 -> byte code offset #49
		// Java source line #85 -> byte code offset #60
		// Java source line #92 -> byte code offset #61
		// Java source line #94 -> byte code offset #64
		// Java source line #95 -> byte code offset #67
		// Java source line #99 -> byte code offset #70
		// Java source line #100 -> byte code offset #78
		// Java source line #101 -> byte code offset #84
		// Java source line #100 -> byte code offset #90
		// Java source line #102 -> byte code offset #95
		// Java source line #103 -> byte code offset #99
		// Java source line #104 -> byte code offset #105
		// Java source line #105 -> byte code offset #111
		// Java source line #106 -> byte code offset #117
		// Java source line #107 -> byte code offset #124
		// Java source line #109 -> byte code offset #128
		// Java source line #110 -> byte code offset #135
		// Java source line #111 -> byte code offset #142
		// Java source line #112 -> byte code offset #149
		// Java source line #113 -> byte code offset #156
		// Java source line #114 -> byte code offset #163
		// Java source line #115 -> byte code offset #170
		// Java source line #116 -> byte code offset #177
		// Java source line #117 -> byte code offset #184
		// Java source line #118 -> byte code offset #191
		// Java source line #119 -> byte code offset #198
		// Java source line #120 -> byte code offset #205
		// Java source line #121 -> byte code offset #212
		// Java source line #122 -> byte code offset #219
		// Java source line #123 -> byte code offset #226
		// Java source line #124 -> byte code offset #233
		// Java source line #125 -> byte code offset #240
		// Java source line #126 -> byte code offset #247
		// Java source line #127 -> byte code offset #254
		// Java source line #128 -> byte code offset #261
		// Java source line #129 -> byte code offset #268
		// Java source line #130 -> byte code offset #275
		// Java source line #131 -> byte code offset #282
		// Java source line #132 -> byte code offset #289
		// Java source line #133 -> byte code offset #296
		// Java source line #134 -> byte code offset #303
		// Java source line #135 -> byte code offset #310
		// Java source line #136 -> byte code offset #317
		// Java source line #137 -> byte code offset #324
		// Java source line #138 -> byte code offset #331
		// Java source line #139 -> byte code offset #338
		// Java source line #140 -> byte code offset #345
		// Java source line #141 -> byte code offset #352
		// Java source line #142 -> byte code offset #359
		// Java source line #143 -> byte code offset #366
		// Java source line #144 -> byte code offset #373
		// Java source line #145 -> byte code offset #380
		// Java source line #146 -> byte code offset #387
		// Java source line #147 -> byte code offset #394
		// Java source line #148 -> byte code offset #401
		// Java source line #149 -> byte code offset #408
		// Java source line #150 -> byte code offset #415
		// Java source line #151 -> byte code offset #422
		// Java source line #152 -> byte code offset #429
		// Java source line #153 -> byte code offset #436
		// Java source line #154 -> byte code offset #443
		// Java source line #155 -> byte code offset #450
		// Java source line #156 -> byte code offset #457
		// Java source line #157 -> byte code offset #464
		// Java source line #158 -> byte code offset #471
		// Java source line #159 -> byte code offset #478
		// Java source line #160 -> byte code offset #485
		// Java source line #161 -> byte code offset #492
		// Java source line #162 -> byte code offset #499
		// Java source line #163 -> byte code offset #506
		// Java source line #164 -> byte code offset #513
		// Java source line #165 -> byte code offset #520
		// Java source line #166 -> byte code offset #527
		// Java source line #167 -> byte code offset #534
		// Java source line #168 -> byte code offset #541
		// Java source line #169 -> byte code offset #548
		// Java source line #170 -> byte code offset #555
		// Java source line #171 -> byte code offset #562
		// Java source line #172 -> byte code offset #569
		// Java source line #173 -> byte code offset #576
		// Java source line #174 -> byte code offset #583
		// Java source line #175 -> byte code offset #590
		// Java source line #176 -> byte code offset #597
		// Java source line #177 -> byte code offset #604
		// Java source line #178 -> byte code offset #611
		// Java source line #179 -> byte code offset #618
		// Java source line #180 -> byte code offset #625
		// Java source line #181 -> byte code offset #633
		// Java source line #182 -> byte code offset #640
		// Java source line #183 -> byte code offset #647
		// Java source line #184 -> byte code offset #654
		// Java source line #185 -> byte code offset #661
		// Java source line #186 -> byte code offset #669
		// Java source line #187 -> byte code offset #677
		// Java source line #188 -> byte code offset #685
		// Java source line #189 -> byte code offset #693
		// Java source line #190 -> byte code offset #701
		// Java source line #191 -> byte code offset #709
		// Java source line #192 -> byte code offset #717
		// Java source line #193 -> byte code offset #725
		// Java source line #194 -> byte code offset #733
		// Java source line #195 -> byte code offset #741
		// Java source line #196 -> byte code offset #748
		// Java source line #197 -> byte code offset #756
		// Java source line #198 -> byte code offset #764
		// Java source line #199 -> byte code offset #772
		// Java source line #200 -> byte code offset #779
		// Java source line #201 -> byte code offset #787
		// Java source line #202 -> byte code offset #795
		// Java source line #203 -> byte code offset #803
		// Java source line #204 -> byte code offset #811
		// Java source line #205 -> byte code offset #819
		// Java source line #206 -> byte code offset #827
		// Java source line #207 -> byte code offset #834
		// Java source line #208 -> byte code offset #842
		// Java source line #209 -> byte code offset #850
		// Java source line #210 -> byte code offset #858
		// Java source line #211 -> byte code offset #866
		// Java source line #212 -> byte code offset #874
		// Java source line #213 -> byte code offset #881
		// Java source line #214 -> byte code offset #888
		// Java source line #215 -> byte code offset #896
		// Java source line #216 -> byte code offset #904
		// Java source line #217 -> byte code offset #912
		// Java source line #218 -> byte code offset #920
		// Java source line #219 -> byte code offset #928
		// Java source line #220 -> byte code offset #935
		// Java source line #221 -> byte code offset #943
		// Java source line #222 -> byte code offset #951
		// Java source line #223 -> byte code offset #959
		// Java source line #224 -> byte code offset #966
		// Java source line #225 -> byte code offset #974
		// Java source line #226 -> byte code offset #982
		// Java source line #227 -> byte code offset #990
		// Java source line #228 -> byte code offset #997
		// Java source line #229 -> byte code offset #1005
		// Java source line #230 -> byte code offset #1013
		// Java source line #231 -> byte code offset #1021
		// Java source line #232 -> byte code offset #1029
		// Java source line #233 -> byte code offset #1037
		// Java source line #234 -> byte code offset #1044
		// Java source line #235 -> byte code offset #1052
		// Java source line #236 -> byte code offset #1060
		// Java source line #237 -> byte code offset #1068
		// Java source line #238 -> byte code offset #1076
		// Java source line #239 -> byte code offset #1084
		// Java source line #240 -> byte code offset #1092
		// Java source line #241 -> byte code offset #1100
		// Java source line #242 -> byte code offset #1108
		// Java source line #243 -> byte code offset #1116
		// Java source line #244 -> byte code offset #1124
		// Java source line #245 -> byte code offset #1131
		// Java source line #246 -> byte code offset #1138
		// Java source line #247 -> byte code offset #1146
		// Java source line #248 -> byte code offset #1154
		// Java source line #249 -> byte code offset #1162
		// Java source line #250 -> byte code offset #1170
		// Java source line #251 -> byte code offset #1178
		// Java source line #252 -> byte code offset #1185
		// Java source line #253 -> byte code offset #1193
		// Java source line #254 -> byte code offset #1201
		// Java source line #255 -> byte code offset #1209
		// Java source line #256 -> byte code offset #1217
		// Java source line #257 -> byte code offset #1225
		// Java source line #258 -> byte code offset #1232
		// Java source line #259 -> byte code offset #1240
		// Java source line #260 -> byte code offset #1248
		// Java source line #261 -> byte code offset #1256
		// Java source line #262 -> byte code offset #1264
		// Java source line #263 -> byte code offset #1272
		// Java source line #264 -> byte code offset #1279
		// Java source line #265 -> byte code offset #1287
		// Java source line #266 -> byte code offset #1295
		// Java source line #267 -> byte code offset #1303
		// Java source line #268 -> byte code offset #1311
		// Java source line #269 -> byte code offset #1319
		// Java source line #270 -> byte code offset #1327
		// Java source line #271 -> byte code offset #1335
		// Java source line #272 -> byte code offset #1354
		// Java source line #273 -> byte code offset #1362
		// Java source line #274 -> byte code offset #1370
		// Java source line #275 -> byte code offset #1377
		// Java source line #276 -> byte code offset #1385
		// Java source line #277 -> byte code offset #1393
		// Java source line #278 -> byte code offset #1401
		// Java source line #279 -> byte code offset #1409
		// Java source line #280 -> byte code offset #1417
		// Java source line #281 -> byte code offset #1425
		// Java source line #282 -> byte code offset #1444
		// Java source line #283 -> byte code offset #1452
		// Java source line #284 -> byte code offset #1460
		// Java source line #285 -> byte code offset #1467
		// Java source line #286 -> byte code offset #1475
		// Java source line #287 -> byte code offset #1483
		// Java source line #288 -> byte code offset #1491
		// Java source line #289 -> byte code offset #1499
		// Java source line #290 -> byte code offset #1507
		// Java source line #291 -> byte code offset #1515
		// Java source line #292 -> byte code offset #1534
		// Java source line #293 -> byte code offset #1542
		// Java source line #294 -> byte code offset #1550
		// Java source line #295 -> byte code offset #1558
		// Java source line #296 -> byte code offset #1566
		// Java source line #297 -> byte code offset #1574
		// Java source line #298 -> byte code offset #1582
		// Java source line #299 -> byte code offset #1590
		// Java source line #300 -> byte code offset #1597
		// Java source line #301 -> byte code offset #1605
		// Java source line #302 -> byte code offset #1613
		// Java source line #303 -> byte code offset #1621
		// Java source line #304 -> byte code offset #1629
		// Java source line #305 -> byte code offset #1637
		// Java source line #306 -> byte code offset #1645
		// Java source line #307 -> byte code offset #1653
		// Java source line #308 -> byte code offset #1661
		// Java source line #309 -> byte code offset #1669
		// Java source line #310 -> byte code offset #1677
		// Java source line #311 -> byte code offset #1685
		// Java source line #312 -> byte code offset #1692
		// Java source line #313 -> byte code offset #1700
		// Java source line #314 -> byte code offset #1708
		// Java source line #315 -> byte code offset #1716
		// Java source line #316 -> byte code offset #1724
		// Java source line #317 -> byte code offset #1732
		// Java source line #318 -> byte code offset #1737
		// Java source line #319 -> byte code offset #1745
		// Java source line #320 -> byte code offset #1749
		// Java source line #322 -> byte code offset #1762
		// Java source line #323 -> byte code offset #1771
		// Java source line #324 -> byte code offset #1776
		// Java source line #325 -> byte code offset #1779
		// Java source line #327 -> byte code offset #1784
		// Java source line #328 -> byte code offset #1788
		// Java source line #329 -> byte code offset #1803
		// Java source line #332 -> byte code offset #1813
		// Java source line #331 -> byte code offset #1824
		// Java source line #332 -> byte code offset #1826
		// Java source line #333 -> byte code offset #1834
		// Java source line #332 -> byte code offset #1837
		// Java source line #334 -> byte code offset #1845
		// Local variable table:
		// start length slot name signature
		// 0 1846 0 this skin_002dconfig_jsp
		// 0 1846 1 request javax.servlet.http.HttpServletRequest
		// 0 1846 2 response javax.servlet.http.HttpServletResponse
		// 6 22 3 _jspx_method String
		// 93 25 4 pageContext javax.servlet.jsp.PageContext
		// 62 1718 5 out javax.servlet.jsp.JspWriter
		// 65 1681 6 _jspx_out javax.servlet.jsp.JspWriter
		// 68 1773 7 _jspx_page_context javax.servlet.jsp.PageContext
		// 1735 73 8 t Throwable
		// 1824 11 9 localObject Object
		// 1787 1 10 localIOException java.io.IOException
		// Exception table:
		// from to target type
		// 70 1732 1735 java/lang/Throwable
		// 1762 1784 1787 java/io/IOException
		// 70 1813 1824 finally
	}
}

/*
 * Location:
 * C:\Users\admin\Desktop\org.jeeframework.gencode-1.5.jar!\org\apache\jsp\
 * static_\common\skin_002dconfig_jsp.class Java compiler version: 7 (51.0)
 * JD-Core Version: 0.7.1
 */